{
    "nodes": [
        {
            "index": 0,
            "atomType": "acceptor",
            "atomTypeInt": "2"
        },
        {
            "index": 1,
            "atomType": "acceptor/donor",
            "atomTypeInt": "10"
        }
    ],
    "links": [
        {
            "source": 0,
            "target": 1,
            "interactionType": "hydrogenbond",
            "interactionTypeInt": "29"
        }
    ],
    "graphproperties": {
        "inputgraphs": [
            143,
            20,
            61,
            253,
            283,
            119,
            297,
            240,
            184,
            107,
            159,
            201,
            15,
            5,
            146,
            188,
            289,
            194,
            19,
            307,
            237,
            241,
            198,
            273,
            296,
            266,
            224,
            233,
            52,
            232,
            9,
            47,
            284,
            230,
            279,
            103,
            76,
            287,
            291,
            71,
            44,
            304,
            68,
            281,
            206,
            95,
            211,
            99,
            139,
            67,
            208,
            229,
            100,
            265,
            202,
            218,
            135,
            60,
            292,
            165,
            300,
            62,
            212,
            57,
            1,
            162,
            129,
            63,
            238,
            261,
            70,
            305,
            216,
            288,
            80,
            301,
            48,
            244,
            262,
            91,
            193,
            45,
            126
        ]
    },
    "group": "1",
    "support": "0.1",
    "id": "6"
}