{
    "nodes": [
        {
            "patterns": [
                8
            ],
            "index": 0,
            "chain": "A",
            "atomType": "donor",
            "atomTypeInt": "5",
            "atomName": "N",
            "residueNumber": "83",
            "residueName": "LEU",
            "color": "#7CB4BE",
            "isLigand": false
        },
        {
            "patterns": [
                8
            ],
            "index": 1,
            "chain": "A",
            "atomType": "acceptor",
            "atomTypeInt": "2",
            "atomName": "O23",
            "residueNumber": "800",
            "residueName": "X86",
            "color": "#9BCE91",
            "isLigand": true
        }
    ],
    "links": [
        {
            "patterns": [
                8
            ],
            "source": 0,
            "target": 1,
            "interactionType": "hydrogenbond",
            "interactionTypeInt": 29,
            "distance": "2.9459876102930203"
        }
    ],
    "id": 142,
    "string": "v 0 5\nv 1 2\ne 0 1 29\n",
    "group": "3",
    "pdbID": "3R71.A"
}